MANIFEST.in
README.rst
setup.cfg
setup.py
microsip_api/__init__.py
microsip_api/__init__.pyc
microsip_api.egg-info/PKG-INFO
microsip_api.egg-info/SOURCES.txt
microsip_api.egg-info/dependency_links.txt
microsip_api.egg-info/top_level.txt
microsip_api/__pycache__/__init__.cpython-37.pyc
microsip_api/__pycache__/__init__.cpython-38.pyc
microsip_api/apps/__init__.py
microsip_api/apps/__pycache__/__init__.cpython-37.pyc
microsip_api/apps/__pycache__/__init__.cpython-38.pyc
microsip_api/apps/administrador/__init__.py
microsip_api/apps/administrador/core.py
microsip_api/apps/administrador/forms.py
microsip_api/apps/administrador/models.py
microsip_api/apps/administrador/send_mail.py
microsip_api/apps/administrador/urls.py
microsip_api/apps/administrador/views.py
microsip_api/apps/administrador/__pycache__/__init__.cpython-37.pyc
microsip_api/apps/administrador/__pycache__/__init__.cpython-38.pyc
microsip_api/apps/administrador/__pycache__/core.cpython-37.pyc
microsip_api/apps/administrador/__pycache__/core.cpython-38.pyc
microsip_api/apps/administrador/__pycache__/forms.cpython-37.pyc
microsip_api/apps/administrador/__pycache__/forms.cpython-38.pyc
microsip_api/apps/administrador/__pycache__/models.cpython-37.pyc
microsip_api/apps/administrador/__pycache__/models.cpython-38.pyc
microsip_api/apps/administrador/__pycache__/send_mail.cpython-37.pyc
microsip_api/apps/administrador/__pycache__/send_mail.cpython-38.pyc
microsip_api/apps/administrador/__pycache__/urls.cpython-37.pyc
microsip_api/apps/administrador/__pycache__/urls.cpython-38.pyc
microsip_api/apps/administrador/__pycache__/views.cpython-37.pyc
microsip_api/apps/administrador/__pycache__/views.cpython-38.pyc
microsip_api/apps/administrador/modules/__init__.py
microsip_api/apps/administrador/modules/__pycache__/__init__.cpython-37.pyc
microsip_api/apps/administrador/modules/__pycache__/__init__.cpython-38.pyc
microsip_api/apps/administrador/modules/sucursales/__init__.py
microsip_api/apps/administrador/modules/sucursales/forms.py
microsip_api/apps/administrador/modules/sucursales/models.py
microsip_api/apps/administrador/modules/sucursales/urls.py
